search_engine/__init__.py
search_engine/baidu_search.py
search_engine/bing_search.py
search_engine/google_search.py
search_engine/search_all.py
search_engine/search_mail.py
search_engine/util.py
search_engine-0.0.6.dist-info/METADATA
search_engine-0.0.6.dist-info/RECORD
search_engine-0.0.6.dist-info/WHEEL
search_engine-0.0.6.dist-info/top_level.txt
